{"is_source_file": true, "format": "JavaScript", "description": "This file is the entry point for a React-based front-end application. It imports React and ReactDOM, along with CSS styling and the main App component. It initializes the React application by rendering the <App /> component into the DOM element with id 'root' inside a React.StrictMode wrapper.", "external_files": ["./App", "./index.css"], "external_methods": ["ReactDOM.createRoot", "root.render"], "published": [], "classes": [], "methods": [{"name": "ReactDOM.createRoot", "description": "Creates a root React node for rendering in the specified DOM element."}, {"name": "root.render", "description": "Renders a React component tree into the root."}], "calls": ["ReactDOM.createRoot", "root.render"], "search-terms": ["React", "ReactDOM", "createRoot", "render", "index.js", "entry point"], "state": 2, "file_id": 8, "knowledge_revision": 25, "git_revision": "9027868e4dee82331e165f2408aec0be34736101", "ctags": [{"_type": "tag", "name": "root", "path": "/home/kavia/workspace/code-generation/simple-notes-app-304266-304275/notes_frontend/src/index.js", "pattern": "/^const root = ReactDOM.createRoot(document.getElementById('root'));$/", "language": "JavaScript", "kind": "constant"}], "hash": "9fc5841375336fc175b49f8767a11383", "format-version": 4, "code-base-name": "notes_frontend", "filename": "notes_frontend/src/index.js", "revision_history": [{"25": "9027868e4dee82331e165f2408aec0be34736101"}]}